exllama/__init__.py
exllama/cuda_ext.py
exllama/generator.py
exllama/lora.py
exllama/model.py
exllama/tokenizer.py
exllama/exllama_ext/cuda_buffers.cu
exllama/exllama_ext/cuda_buffers.cuh
exllama/exllama_ext/cuda_compat.cuh
exllama/exllama_ext/exllama_ext.cpp
exllama/exllama_ext/hip_compat.cuh
exllama/exllama_ext/matrix.cuh
exllama/exllama_ext/tuning.h
exllama/exllama_ext/util.cuh
exllama/exllama_ext/cpu_func/rep_penalty.cpp
exllama/exllama_ext/cpu_func/rep_penalty.h
exllama/exllama_ext/cuda_func/column_remap.cu
exllama/exllama_ext/cuda_func/column_remap.cuh
exllama/exllama_ext/cuda_func/half_matmul.cu
exllama/exllama_ext/cuda_func/half_matmul.cuh
exllama/exllama_ext/cuda_func/q4_attn.cu
exllama/exllama_ext/cuda_func/q4_attn.cuh
exllama/exllama_ext/cuda_func/q4_matmul.cu
exllama/exllama_ext/cuda_func/q4_matmul.cuh
exllama/exllama_ext/cuda_func/q4_matrix.cu
exllama/exllama_ext/cuda_func/q4_matrix.cuh
exllama/exllama_ext/cuda_func/q4_mlp.cu
exllama/exllama_ext/cuda_func/q4_mlp.cuh
exllama/exllama_ext/cuda_func/rms_norm.cu
exllama/exllama_ext/cuda_func/rms_norm.cuh
exllama/exllama_ext/cuda_func/rope.cu
exllama/exllama_ext/cuda_func/rope.cuh
exllama-0.1.0.dist-info/LICENSE
exllama-0.1.0.dist-info/METADATA
exllama-0.1.0.dist-info/WHEEL
exllama-0.1.0.dist-info/top_level.txt
exllama-0.1.0.dist-info/RECORD
