Metadata-Version: 2.1
Name: exllama
Version: 0.1.0
Summary: UNKNOWN
Home-page: UNKNOWN
License: UNKNOWN
Platform: UNKNOWN
Requires-Python: >=3.9
Requires-Dist: ninja (==1.11.1)
Requires-Dist: safetensors (==0.3.1)
Requires-Dist: sentencepiece (>=0.1.97)
Requires-Dist: torch (>=2.0.1)
